sila/__init__.py
sila/py.typed
sila/datetime/__init__.py
sila/datetime/date.py
sila/framework/__init__.py
sila/framework/binary_transfer/__init__.py
sila/framework/binary_transfer/binary_transfer.py
sila/framework/binary_transfer/binary_transfer_error.py
sila/framework/binary_transfer/binary_transfer_handler.py
sila/framework/binary_transfer/create_binary_request.py
sila/framework/binary_transfer/create_binary_response.py
sila/framework/binary_transfer/delete_binary_request.py
sila/framework/binary_transfer/delete_binary_response.py
sila/framework/binary_transfer/download_chunk_request.py
sila/framework/binary_transfer/download_chunk_response.py
sila/framework/binary_transfer/get_binary_info_request.py
sila/framework/binary_transfer/get_binary_info_response.py
sila/framework/binary_transfer/upload_chunk_request.py
sila/framework/binary_transfer/upload_chunk_response.py
sila/framework/cloud/__init__.py
sila/framework/cloud/cancel_request.py
sila/framework/cloud/client_message.py
sila/framework/cloud/cloud_metadata.py
sila/framework/cloud/command_confirmation_response.py
sila/framework/cloud/command_execution_request.py
sila/framework/cloud/command_execution_response.py
sila/framework/cloud/command_parameter.py
sila/framework/cloud/command_response_request.py
sila/framework/cloud/create_binary_upload_request.py
sila/framework/cloud/metadata_request.py
sila/framework/cloud/metadata_response.py
sila/framework/cloud/observable_command_response.py
sila/framework/cloud/property_request.py
sila/framework/cloud/property_response.py
sila/framework/cloud/server_message.py
sila/framework/cloud/unobservable_command_response.py
sila/framework/command/__init__.py
sila/framework/command/command.py
sila/framework/command/command_confirmation.py
sila/framework/command/command_execution.py
sila/framework/command/command_execution_info.py
sila/framework/command/command_execution_uuid.py
sila/framework/command/observable_command.py
sila/framework/command/unobservable_command.py
unitelabs_sila-0.7.0.dist-info/METADATA
unitelabs_sila-0.7.0.dist-info/WHEEL
unitelabs_sila-0.7.0.dist-info/licenses/LICENSE
unitelabs_sila-0.7.0.dist-info/RECORD
