Metadata-Version: 2.4
Name: unitelabs-sila
Version: 0.7.0
Summary: An un-opinionated SiLA 2 library.
Project-URL: homepage, https://sila-standard.com
Project-URL: repository, https://gitlab.com/unitelabs/sila2/sila-python
Project-URL: documentation, https://gitlab.com/unitelabs/sila2/sila-python/-/README.md
Project-URL: Bug Tracker, https://gitlab.com/unitelabs/sila2/sila-python/-/issues
Author-email: UniteLabs <developers+sila@unitelabs.io>
License-Expression: MIT
License-File: LICENSE
Keywords: SiLA 2,automation,connectivity,laboratory
Classifier: Development Status :: 4 - Beta
Classifier: Intended Audience :: Developers
Classifier: Intended Audience :: Healthcare Industry
Classifier: Intended Audience :: Science/Research
Classifier: License :: OSI Approved :: MIT License
Classifier: Operating System :: OS Independent
Classifier: Programming Language :: Python :: 3 :: Only
Classifier: Programming Language :: Python :: 3.10
Classifier: Programming Language :: Python :: 3.11
Classifier: Programming Language :: Python :: 3.12
Classifier: Programming Language :: Python :: 3.13
Classifier: Programming Language :: Python :: 3.14
Classifier: Topic :: Software Development :: Libraries
Requires-Python: <4.0,>=3.10
Requires-Dist: grpcio>=1.70.0
Requires-Dist: jsonschema~=4.25
Requires-Dist: typing-extensions
Requires-Dist: xmlschema~=4.2
Requires-Dist: zeroconf>=0.147.0
Provides-Extra: dev
Requires-Dist: commitizen; extra == 'dev'
Requires-Dist: cryptography>=43.0.3; extra == 'dev'
Requires-Dist: pre-commit; extra == 'dev'
Requires-Dist: ruff; extra == 'dev'
Provides-Extra: docs
Requires-Dist: unitelabs-jsondocs[clog]~=0.2.0; extra == 'docs'
Provides-Extra: test
Requires-Dist: pytest; extra == 'test'
Requires-Dist: pytest-asyncio; extra == 'test'
Requires-Dist: pytest-cov; extra == 'test'
